{"cameraMode":{"drawMode":0,"name":"Shaded","section":"Shading Mode"},"sceneLighting":false,"audioPlay":false,"sceneViewState":{"m_AlwaysRefresh":false,"showFog":true,"showSkybox":false,"showFlares":true,"showImageEffects":true,"showParticleSystems":true,"showVisualEffectGraphs":true,"m_FxEnabled":true},"in2DMode":false,"pivot":{"x":225.60400390625,"y":2.490830183029175,"z":203.06997680664063},"rotation":{"x":0.10202142596244812,"y":0.8674491047859192,"z":-0.44480058550834658,"w":0.19891227781772614},"size":5.343585968017578,"orthographic":false}